animeworld/__init__.py
animeworld/anime.py
animeworld/episodio.py
animeworld/exceptions.py
animeworld/utility.py
animeworld/servers/AnimeWorld_Server.py
animeworld/servers/Server.py
animeworld/servers/Streamtape.py
animeworld/servers/YouTube.py
animeworld/servers/__init__.py
animeworld-1.6.8.dist-info/licenses/LICENSE
animeworld-1.6.8.dist-info/METADATA
animeworld-1.6.8.dist-info/WHEEL
animeworld-1.6.8.dist-info/top_level.txt
animeworld-1.6.8.dist-info/RECORD
