Metadata-Version: 2.4
Name: animeworld
Version: 1.6.8
Summary: AnimeWorld UNOFFICIAL API
License: MIT License
Project-URL: Homepage, https://mainkronos.github.io/AnimeWorld-API/
Project-URL: Documentation, https://mainkronos.github.io/AnimeWorld-API/
Project-URL: Repository, https://github.com/MainKronos/AnimeWorld-API.git
Project-URL: Issues, https://github.com/MainKronos/AnimeWorld-API/issues
Keywords: anime,animeworld,animeworld-api,api
Classifier: Development Status :: 5 - Production/Stable
Classifier: Intended Audience :: Developers
Classifier: Topic :: Internet :: WWW/HTTP :: Indexing/Search
Classifier: Topic :: Software Development :: Libraries
Classifier: Programming Language :: Python :: 3
Classifier: License :: OSI Approved :: MIT License
Requires-Python: >=3.11
License-File: LICENSE
Requires-Dist: httpx
Requires-Dist: httpx[http2]
Requires-Dist: youtube_dl
Requires-Dist: beautifulsoup4
Dynamic: license-file
